src/__init__.py
src/guess_one_shot.py
src/guess_xsd_user_input.py
src/repeated_one_shot.py
src/xsd_guess.py
src/xsd_guess_single.py
guess_xsd_type-0.1.dist-info/LICENSE.txt
guess_xsd_type-0.1.dist-info/METADATA
guess_xsd_type-0.1.dist-info/WHEEL
guess_xsd_type-0.1.dist-info/top_level.txt
guess_xsd_type-0.1.dist-info/RECORD
