Metadata-Version: 2.1
Name: guess-xsd-type
Version: 0.1
Summary: XSD data type recommender
Home-page: https://github.com/DHLab-nl/guess_xsd_type
Author: Richard L. Zijdeman
Author-email: richard.zijdeman@iisg.nl
License: UNKNOWN
Platform: UNKNOWN
Classifier: Programming Language :: Python :: 3
Classifier: License :: OSI Approved :: MIT License
Classifier: Operating System :: OS Independent
Requires-Python: >=3.6
